entityextractionpack/__init__.py
entityextractionpack/extraction.py
entityextractionpack/OBOL_SAMPLE.pdf
entityextractionpack/SWB_SAMPLE.pdf
entityextractionpack/utils.py
entityextractionpack-0.1.0.dist-info/METADATA
entityextractionpack-0.1.0.dist-info/WHEEL
entityextractionpack-0.1.0.dist-info/RECORD
